{
  "generated_at": "2026-01-03T18:19:25.285369+08:00",
  "total_titles_processed": 315,
  "failed_sources": [],
  "trends": [
    {
      "keyword_group": "乌克兰 俄乌战争 国际局势 战争",
      "match_count": 2,
      "titles": [
        {
          "title": "俄罗斯国防部：俄罗斯军队已占领乌克兰顿涅茨克地区的邦达尔内。",
          "url": "https://flash.jin10.com/detail/20260103172531674800",
          "source": "金十数据",
          "ranks": [
            16
          ],
          "is_new": false,
          "appearance_count": 1,
          "time_info": "18时19分"
        },
        {
          "title": "美参议员警告称：美国在委内瑞拉“没有重大国家利益”无需发动战争",
          "url": "https://flash.jin10.com/detail/20260103165432698800",
          "source": "金十数据",
          "ranks": [
            29
          ],
          "is_new": false,
          "appearance_count": 1,
          "time_info": "18时19分"
        }
      ]
    }
  ],
  "report_image_url": "https://joyce677.github.io/TrendRadar/img/news.jpg"
}